[
    {
        "unique_id": 480,
        "genre": "Caribbean Folk ",
        "artist": "Various",
        "song": "Carribean Island Music - Songs and Dances of Haiti, The Dominican Republic and Jamaica",
        "year": "(1972)",
        "url": "https://www.youtube.com/results?search_query=Various-Carribean%20Island%20Music%20-%20Songs%20and%20Dances%20of%20Haiti%2C%20The%20Dominican%20Republic%20and%20Jamaica",
        "enriched": true,
        "youtube": {
            "kind": "youtube#searchResult",
            "etag": "\"0UM_wBUsFuT6ekiIlwaHvyqc80M/dqqx1ttUamkxfH6DT9OaaBPGzYc\"",
            "id": {
                "kind": "youtube#video",
                "videoId": "BVybOnglW_k"
            },
            "snippet": {
                "publishedAt": "2017-09-08T18:42:33.000Z",
                "channelId": "UC-yXuc1__OzjwpsJPlxYUCQ",
                "title": "Hood Celebrityy &quot;Island Girls&quot; Feat. Cardi B, Josh X &amp; Young Chow (WSHH Exclusive)",
                "description": "Watch the official music video for \"Island Girls\" by Hood Celebrityy Feat. Cardi B, Josh X & Young Chow. Underestimated The Album available now!",
                "thumbnails": {
                    "default": {
                        "url": "https://i.ytimg.com/vi/BVybOnglW_k/default.jpg",
                        "width": 120,
                        "height": 90
                    },
                    "medium": {
                        "url": "https://i.ytimg.com/vi/BVybOnglW_k/mqdefault.jpg",
                        "width": 320,
                        "height": 180
                    },
                    "high": {
                        "url": "https://i.ytimg.com/vi/BVybOnglW_k/hqdefault.jpg",
                        "width": 480,
                        "height": 360
                    }
                },
                "channelTitle": "WORLDSTARHIPHOP",
                "liveBroadcastContent": "none"
            }
        }
    }
]