[
    {
        "unique_id": 484,
        "genre": "Goombay",
        "artist": "Various",
        "song": "Bahamas Goombay",
        "year": "(1951-1959)",
        "url": "https://www.youtube.com/results?search_query=Various-Bahamas%20Goombay",
        "enriched": true,
        "youtube": {
            "kind": "youtube#searchResult",
            "etag": "\"0UM_wBUsFuT6ekiIlwaHvyqc80M/S1dkxRZaptLEjEPuScwDWx9G3vM\"",
            "id": {
                "kind": "youtube#video",
                "videoId": "E5FxzVIEME4"
            },
            "snippet": {
                "publishedAt": "2016-03-12T19:58:34.000Z",
                "channelId": "UCMePB5lC-wvTEIuXgtzYyVw",
                "title": "Charlie Adamson Sings Goombay! The Folk Songs Of The Bahamas",
                "description": "FOR BETTER AND UNINTERRUPTED PLAYBACK PLEASE SWITCH TO *HD 1080p PLAYBACK* *DISCLAIMER* NO COPYRIGHT INFRINGEMENT ...",
                "thumbnails": {
                    "default": {
                        "url": "https://i.ytimg.com/vi/E5FxzVIEME4/default.jpg",
                        "width": 120,
                        "height": 90
                    },
                    "medium": {
                        "url": "https://i.ytimg.com/vi/E5FxzVIEME4/mqdefault.jpg",
                        "width": 320,
                        "height": 180
                    },
                    "high": {
                        "url": "https://i.ytimg.com/vi/E5FxzVIEME4/hqdefault.jpg",
                        "width": 480,
                        "height": 360
                    }
                },
                "channelTitle": "INVIGORATION",
                "liveBroadcastContent": "none"
            }
        }
    }
]