[
    {
        "unique_id": 115,
        "genre": "Hindustani Classical ",
        "artist": "Ravi Shankar",
        "song": "Music of India - Three Classical R\u0101gas",
        "year": "(1956)",
        "url": "https://www.youtube.com/results?search_query=Ravi%20Shankar-Music%20of%20India%20-%20Three%20Classical%20R%C4%81gas",
        "youtube": {
            "kind": "youtube#searchResult",
            "etag": "\"nlUZBA6NbTS7q9G8D1GljyfTIWI/wJqlkihkCcZr1ukjaoKh5L5h6hk\"",
            "id": {
                "kind": "youtube#video",
                "videoId": "krT_hGvEvhg"
            },
            "snippet": {
                "publishedAt": "2017-04-23T19:00:03.000Z",
                "channelId": "UChu6I4fYWUAiQdWr-3YIb5w",
                "title": "Ravi Shankar - Three Ragas (Remastered) (Full Album)",
                "description": "Ravi Shankar - Three Ragas (Remastered) (Full Album) --------------------------------- Tip: click on the time and listen your favorite song Track list: ...",
                "thumbnails": {
                    "default": {
                        "url": "https://i.ytimg.com/vi/krT_hGvEvhg/default.jpg",
                        "width": 120,
                        "height": 90
                    },
                    "medium": {
                        "url": "https://i.ytimg.com/vi/krT_hGvEvhg/mqdefault.jpg",
                        "width": 320,
                        "height": 180
                    },
                    "high": {
                        "url": "https://i.ytimg.com/vi/krT_hGvEvhg/hqdefault.jpg",
                        "width": 480,
                        "height": 360
                    }
                },
                "channelTitle": "Begarmundi records",
                "liveBroadcastContent": "none"
            }
        },
        "enriched": true
    }
]