[
    {
        "unique_id": 670,
        "genre": "Jazz Fusion ",
        "artist": "Miles Davis",
        "song": "In a Silent Way",
        "year": "(1969)",
        "url": "https://www.youtube.com/results?search_query=Miles%20Davis-In%20a%20Silent%20Way",
        "enriched": true,
        "youtube": {
            "kind": "youtube#searchResult",
            "etag": "\"0UM_wBUsFuT6ekiIlwaHvyqc80M/j7-pX5qJSGc4OOogNPhN5hZmbBE\"",
            "id": {
                "kind": "youtube#video",
                "videoId": "lQKt7DTKyJU"
            },
            "snippet": {
                "publishedAt": "2015-08-15T21:05:35.000Z",
                "channelId": "UCcy5XraMbx5iEfz_wmFtNHQ",
                "title": "Miles Davis - In a Silent Way - 1969",
                "description": "Miles Davis - In a Silent Way - 1969 01- Shhh / Peaceful 02- In a Silent Way / It's about That Time Miles Davis \u2013 trumpet, composer Wayne Shorter \u2013 soprano ...",
                "thumbnails": {
                    "default": {
                        "url": "https://i.ytimg.com/vi/lQKt7DTKyJU/default.jpg",
                        "width": 120,
                        "height": 90
                    },
                    "medium": {
                        "url": "https://i.ytimg.com/vi/lQKt7DTKyJU/mqdefault.jpg",
                        "width": 320,
                        "height": 180
                    },
                    "high": {
                        "url": "https://i.ytimg.com/vi/lQKt7DTKyJU/hqdefault.jpg",
                        "width": 480,
                        "height": 360
                    }
                },
                "channelTitle": "Andr\u00e9 Azevedo",
                "liveBroadcastContent": "none"
            }
        }
    },
    {
        "unique_id": 671,
        "genre": "Jazz Fusion ",
        "artist": "The Mahavishnu Orchestra With John McLaughlin",
        "song": "The Inner Mounting Flame",
        "year": "(1971)",
        "url": "https://www.youtube.com/results?search_query=The%20Mahavishnu%20Orchestra%20With%20John%20McLaughlin-The%20Inner%20Mounting%20Flame",
        "enriched": true,
        "youtube": {
            "kind": "youtube#searchResult",
            "etag": "\"0UM_wBUsFuT6ekiIlwaHvyqc80M/4ENgHpN4Aw237FGy_4RRoZTHYXk\"",
            "id": {
                "kind": "youtube#video",
                "videoId": "5ofh_S52Uks"
            },
            "snippet": {
                "publishedAt": "2016-02-21T19:33:08.000Z",
                "channelId": "UCi3QBDoFjj3ZXFKt8JpsKuQ",
                "title": "The Mahavishnu Orchestra - The Inner Mounting Flame (1971) - Full Album (HQ)",
                "description": "Tracks: 1. Meeting of the Spirits 00:00 2. Dawn 06:52 3. The Noonward Race 12:04 4. A Lotus On Irish Streams 18:33 5. Vital Transformation 24:15 6. The Dance ...",
                "thumbnails": {
                    "default": {
                        "url": "https://i.ytimg.com/vi/5ofh_S52Uks/default.jpg",
                        "width": 120,
                        "height": 90
                    },
                    "medium": {
                        "url": "https://i.ytimg.com/vi/5ofh_S52Uks/mqdefault.jpg",
                        "width": 320,
                        "height": 180
                    },
                    "high": {
                        "url": "https://i.ytimg.com/vi/5ofh_S52Uks/hqdefault.jpg",
                        "width": 480,
                        "height": 360
                    }
                },
                "channelTitle": "M\u00fasica Livre",
                "liveBroadcastContent": "none"
            }
        }
    },
    {
        "unique_id": 672,
        "genre": "Jazz Fusion ",
        "artist": "Chick Corea",
        "song": "Return to Forever",
        "year": "(1972)",
        "url": "https://www.youtube.com/results?search_query=Chick%20Corea-Return%20to%20Forever",
        "enriched": true,
        "youtube": {
            "kind": "youtube#searchResult",
            "etag": "\"0UM_wBUsFuT6ekiIlwaHvyqc80M/Pp0sKYozZw19b6grT3uIZcD5FK8\"",
            "id": {
                "kind": "youtube#playlist",
                "playlistId": "PLfdMKJMGPPtzmsRVWbA23XQwMnrAM2TCZ"
            },
            "snippet": {
                "publishedAt": "2017-02-15T01:01:47.000Z",
                "channelId": "UC9qF-BPjCLKe02YukJCWk2A",
                "title": "Chick Corea: Return to Forever (1972)",
                "description": "https://de.wikipedia.org/wiki/Return_to_Forever_(Chick-Corea-Album) https://en.wikipedia.org/wiki/Return_to_Forever_(Chick_Corea_album) Chick Corea: ...",
                "channelTitle": "thomas brunner",
                "liveBroadcastContent": "none"
            }
        }
    },
    {
        "unique_id": 673,
        "genre": "Jazz Fusion ",
        "artist": "Herbie Hancock",
        "song": "Sextant",
        "year": "(1973)",
        "url": "https://www.youtube.com/results?search_query=Herbie%20Hancock-Sextant",
        "enriched": true,
        "youtube": {
            "kind": "youtube#searchResult",
            "etag": "\"8jEFfXBrqiSrcF6Ee7MQuz8XuAM/pD3l--YoT_L3ylJRroRvbu5ZL_Y\"",
            "id": {
                "kind": "youtube#video",
                "videoId": "6Mz5rR0y0fM"
            },
            "snippet": {
                "publishedAt": "2015-08-17T19:49:43.000Z",
                "channelId": "UCf-sYveHqWLlDzD3LSzeDZg",
                "title": "Herbie Hancock - Sextant [Full album] | 1973",
                "description": "Tracklist: \"Rain Dance\" - 00:00 \"Hidden Shadows\" - 09:16 \"Hornets\" - 19:27 Personnel: MWANDISHI (Herbie Hancock) - piano, Fender Rhodes, Hohner D6 ...",
                "thumbnails": {
                    "default": {
                        "url": "https://i.ytimg.com/vi/6Mz5rR0y0fM/default.jpg",
                        "width": 120,
                        "height": 90
                    },
                    "medium": {
                        "url": "https://i.ytimg.com/vi/6Mz5rR0y0fM/mqdefault.jpg",
                        "width": 320,
                        "height": 180
                    },
                    "high": {
                        "url": "https://i.ytimg.com/vi/6Mz5rR0y0fM/hqdefault.jpg",
                        "width": 480,
                        "height": 360
                    }
                },
                "channelTitle": "Jorge Valdiviezo",
                "liveBroadcastContent": "none"
            }
        }
    },
    {
        "unique_id": 674,
        "genre": "Jazz Fusion ",
        "artist": "Jan Hammer",
        "song": "The First Seven Days",
        "year": "(1975)",
        "url": "https://www.youtube.com/results?search_query=Jan%20Hammer-The%20First%20Seven%20Days",
        "enriched": true,
        "youtube": {
            "kind": "youtube#searchResult",
            "etag": "\"8jEFfXBrqiSrcF6Ee7MQuz8XuAM/Xw6ywh2taiiBtYy7Akj80nuK_5Y\"",
            "id": {
                "kind": "youtube#video",
                "videoId": "yimHVscaGMk"
            },
            "snippet": {
                "publishedAt": "2016-07-04T04:33:01.000Z",
                "channelId": "UCcBIYR2L-I3t8gOfCCKCjAw",
                "title": "Jan Hammer - The First Seven Days (entire opera)",
                "description": "composed by Jan Hammer recorded at Red Gate Studio, Kent, New York, US (1975) SIDE A: 04'35'' - 00:00 - 1) Darkness/Earth in Search of a Sun 06'45'' ...",
                "thumbnails": {
                    "default": {
                        "url": "https://i.ytimg.com/vi/yimHVscaGMk/default.jpg",
                        "width": 120,
                        "height": 90
                    },
                    "medium": {
                        "url": "https://i.ytimg.com/vi/yimHVscaGMk/mqdefault.jpg",
                        "width": 320,
                        "height": 180
                    },
                    "high": {
                        "url": "https://i.ytimg.com/vi/yimHVscaGMk/hqdefault.jpg",
                        "width": 480,
                        "height": 360
                    }
                },
                "channelTitle": "Stefano Ruotolo",
                "liveBroadcastContent": "none"
            }
        }
    },
    {
        "unique_id": 675,
        "genre": "Jazz Fusion ",
        "artist": "Return to Forever",
        "song": "Romantic Warrior",
        "year": "(1976)",
        "url": "https://www.youtube.com/results?search_query=Return%20to%20Forever-Romantic%20Warrior",
        "enriched": true,
        "youtube": {
            "kind": "youtube#searchResult",
            "etag": "\"8jEFfXBrqiSrcF6Ee7MQuz8XuAM/vhWmQd0Xi-oyqNYj16PBobrG7fI\"",
            "id": {
                "kind": "youtube#video",
                "videoId": "6ETla9zs5SI"
            },
            "snippet": {
                "publishedAt": "2017-03-18T14:22:06.000Z",
                "channelId": "UCngS9iz1UolUaqD31a4jGcA",
                "title": "Return to Forever - The Romantic Warrior HQ",
                "description": "Album: The Romantic Warrior (1976)",
                "thumbnails": {
                    "default": {
                        "url": "https://i.ytimg.com/vi/6ETla9zs5SI/default.jpg",
                        "width": 120,
                        "height": 90
                    },
                    "medium": {
                        "url": "https://i.ytimg.com/vi/6ETla9zs5SI/mqdefault.jpg",
                        "width": 320,
                        "height": 180
                    },
                    "high": {
                        "url": "https://i.ytimg.com/vi/6ETla9zs5SI/hqdefault.jpg",
                        "width": 480,
                        "height": 360
                    }
                },
                "channelTitle": "Hiawatha",
                "liveBroadcastContent": "none"
            }
        }
    },
    {
        "unique_id": 676,
        "genre": "Jazz Fusion ",
        "artist": "Ornette Coleman",
        "song": "Dancing in Your Head",
        "year": "(1977)",
        "url": "https://www.youtube.com/results?search_query=Ornette%20Coleman-Dancing%20in%20Your%20Head",
        "enriched": true,
        "youtube": {
            "kind": "youtube#searchResult",
            "etag": "\"8jEFfXBrqiSrcF6Ee7MQuz8XuAM/PMP70up_kBj2N5C09elzildbdRo\"",
            "id": {
                "kind": "youtube#video",
                "videoId": "23QVY94tAj0"
            },
            "snippet": {
                "publishedAt": "2013-12-28T23:51:31.000Z",
                "channelId": "UCp7w0g1AjIAOFyjqr8puJgQ",
                "title": "Ornette Coleman - Dancing In Your Head (1977)",
                "description": "Dancing in Your Head es un \u00e1lbum de estudio del artista de jazz Ornette Coleman, lanzado en 1977 por Horizon Records. Fue donde por primera vez presento ...",
                "thumbnails": {
                    "default": {
                        "url": "https://i.ytimg.com/vi/23QVY94tAj0/default.jpg",
                        "width": 120,
                        "height": 90
                    },
                    "medium": {
                        "url": "https://i.ytimg.com/vi/23QVY94tAj0/mqdefault.jpg",
                        "width": 320,
                        "height": 180
                    },
                    "high": {
                        "url": "https://i.ytimg.com/vi/23QVY94tAj0/hqdefault.jpg",
                        "width": 480,
                        "height": 360
                    }
                },
                "channelTitle": "Facundo Murias",
                "liveBroadcastContent": "none"
            }
        }
    },
    {
        "unique_id": 677,
        "genre": "Jazz Fusion ",
        "artist": "Al Di Meola",
        "song": "Elegant Gypsy",
        "year": "(1977)",
        "url": "https://www.youtube.com/results?search_query=Al%20Di%20Meola-Elegant%20Gypsy",
        "enriched": true,
        "youtube": {
            "kind": "youtube#searchResult",
            "etag": "\"8jEFfXBrqiSrcF6Ee7MQuz8XuAM/vgkaqQFqNuzMkoAqC5IWnoD_XcY\"",
            "id": {
                "kind": "youtube#video",
                "videoId": "9Y7xw2k6mH4"
            },
            "snippet": {
                "publishedAt": "2018-08-29T15:28:51.000Z",
                "channelId": "UCu61XJ7klWC_e6PEqsSCKIg",
                "title": "Al Di Meola -  Elegant Gypsy - (1977  full album)",
                "description": "",
                "thumbnails": {
                    "default": {
                        "url": "https://i.ytimg.com/vi/9Y7xw2k6mH4/default.jpg",
                        "width": 120,
                        "height": 90
                    },
                    "medium": {
                        "url": "https://i.ytimg.com/vi/9Y7xw2k6mH4/mqdefault.jpg",
                        "width": 320,
                        "height": 180
                    },
                    "high": {
                        "url": "https://i.ytimg.com/vi/9Y7xw2k6mH4/hqdefault.jpg",
                        "width": 480,
                        "height": 360
                    }
                },
                "channelTitle": "Iacoblev Daniel Barau",
                "liveBroadcastContent": "none"
            }
        }
    },
    {
        "unique_id": 678,
        "genre": "Jazz Fusion ",
        "artist": "Sun Ra",
        "song": "Lanquidity",
        "year": "(1978)",
        "url": "https://www.youtube.com/results?search_query=Sun%20Ra-Lanquidity",
        "enriched": true,
        "youtube": {
            "kind": "youtube#searchResult",
            "etag": "\"8jEFfXBrqiSrcF6Ee7MQuz8XuAM/6M7DfFAeRA6beAiil2M1QutpP_0\"",
            "id": {
                "kind": "youtube#video",
                "videoId": "238Dh6N9GLg"
            },
            "snippet": {
                "publishedAt": "2018-07-27T13:41:30.000Z",
                "channelId": "UC-VbS62vD2JDiKGru9E_Fxw",
                "title": "Sun Ra - Lanquidity (1978) (Full Album)",
                "description": "Alto Saxophone, Oboe, Flute \u2013 Marshall Allen Baritone Saxophone \u2013 Julian Presley Baritone Saxophone, Flute \u2013 Danny Thompson Bass \u2013 Richard Williams ...",
                "thumbnails": {
                    "default": {
                        "url": "https://i.ytimg.com/vi/238Dh6N9GLg/default.jpg",
                        "width": 120,
                        "height": 90
                    },
                    "medium": {
                        "url": "https://i.ytimg.com/vi/238Dh6N9GLg/mqdefault.jpg",
                        "width": 320,
                        "height": 180
                    },
                    "high": {
                        "url": "https://i.ytimg.com/vi/238Dh6N9GLg/hqdefault.jpg",
                        "width": 480,
                        "height": 360
                    }
                },
                "channelTitle": "Jazz Time with Jarvis X",
                "liveBroadcastContent": "none"
            }
        }
    },
    {
        "unique_id": 679,
        "genre": "Jazz Fusion ",
        "artist": "Bill Connors",
        "song": "Step It",
        "year": "(1984)",
        "url": "https://www.youtube.com/results?search_query=Bill%20Connors-Step%20It",
        "enriched": true,
        "youtube": {
            "kind": "youtube#searchResult",
            "etag": "\"8jEFfXBrqiSrcF6Ee7MQuz8XuAM/CEATKYuUToQkGVD8ao_gq9f0W0U\"",
            "id": {
                "kind": "youtube#playlist",
                "playlistId": "PLooF1k9qoOZjIw0ZTBHx3tsmN-fqVrcvw"
            },
            "snippet": {
                "publishedAt": "2013-07-23T22:46:36.000Z",
                "channelId": "UCpXgiNAjvXYMVRm3awRKemA",
                "title": "Bill Connors / Step It!",
                "description": "This Playlist Created by ELPEE.",
                "thumbnails": {
                    "default": {
                        "url": "https://i.ytimg.com/vi/40XNBq-vPXo/default.jpg",
                        "width": 120,
                        "height": 90
                    },
                    "medium": {
                        "url": "https://i.ytimg.com/vi/40XNBq-vPXo/mqdefault.jpg",
                        "width": 320,
                        "height": 180
                    },
                    "high": {
                        "url": "https://i.ytimg.com/vi/40XNBq-vPXo/hqdefault.jpg",
                        "width": 480,
                        "height": 360
                    }
                },
                "channelTitle": "akirajb",
                "liveBroadcastContent": "none"
            }
        }
    }
]