[
    {
        "unique_id": 255,
        "genre": "Laika ",
        "artist": "Vassilis Tsitsanis",
        "song": "\u03a4\u03c3\u03b9\u03c4\u03c3\u03ac\u03bd\u03b7\u03c2 [T\u03b1 \u03ba\u03bb\u03b5\u03b9\u03b4\u03b9\u03ac]",
        "year": "(1966)",
        "url": "https://www.youtube.com/results?search_query=Vassilis%20Tsitsanis-%CE%A4%CF%83%CE%B9%CF%84%CF%83%CE%AC%CE%BD%CE%B7%CF%82%20%5BT%CE%B1%20%CE%BA%CE%BB%CE%B5%CE%B9%CE%B4%CE%B9%CE%AC%5D",
        "youtube": {
            "kind": "youtube#searchResult",
            "etag": "\"nlUZBA6NbTS7q9G8D1GljyfTIWI/4SXzWhIb56wMvai1guVvcyMxhgU\"",
            "id": {
                "kind": "youtube#playlist",
                "playlistId": "PLCA25965176A791F6"
            },
            "snippet": {
                "publishedAt": "2011-01-23T20:41:20.000Z",
                "channelId": "UCjpN3R3iuWnXNqiDaJpzRNQ",
                "title": "\u03a4\u03a3\u0399\u03a4\u03a3\u0391\u039d\u0397\u03a3 - \u03a4\u0391 \u039a\u039b\u0395\u0399\u0394\u0399\u0391 (1968)",
                "description": "\u039c\u03c0\u03bf\u03c5\u03b6\u03bf\u03cd\u03ba\u03b9: \u039a\u03ce\u03c3\u03c4\u03b1\u03c2 \u03a0\u03b1\u03c0\u03b1\u03b4\u03cc\u03c0\u03bf\u03c5\u03bb\u03bf\u03c2 & \u039b\u03ac\u03ba\u03b7\u03c2 \u039a\u03b1\u03c1\u03bd\u03ad\u03b6\u03b7\u03c2.",
                "thumbnails": {
                    "default": {
                        "url": "https://i.ytimg.com/vi/yudjSlocCyA/default.jpg",
                        "width": 120,
                        "height": 90
                    },
                    "medium": {
                        "url": "https://i.ytimg.com/vi/yudjSlocCyA/mqdefault.jpg",
                        "width": 320,
                        "height": 180
                    },
                    "high": {
                        "url": "https://i.ytimg.com/vi/yudjSlocCyA/hqdefault.jpg",
                        "width": 480,
                        "height": 360
                    }
                },
                "channelTitle": "\u0395\u03bb\u03ad\u03bd\u03b7 \u039c\u03c0\u03ad\u03b7",
                "liveBroadcastContent": "none"
            }
        },
        "enriched": true
    }
]