[
    {
        "unique_id": 237,
        "genre": "Slovenian Folk ",
        "artist": "Slavko Avsenik und seine Original Oberkrainer",
        "song": "Ein Feuerwerk der Musik",
        "year": "(1986)",
        "url": "https://www.youtube.com/results?search_query=Slavko%20Avsenik%20und%20seine%20Original%20Oberkrainer-Ein%20Feuerwerk%20der%20Musik",
        "youtube": {
            "kind": "youtube#searchResult",
            "etag": "\"nlUZBA6NbTS7q9G8D1GljyfTIWI/H-hQiPmcx_friOyrl-LSKURsZh4\"",
            "id": {
                "kind": "youtube#video",
                "videoId": "4GMzb-89XKI"
            },
            "snippet": {
                "publishedAt": "2019-05-05T09:13:01.000Z",
                "channelId": "UC4qrhtoB9ulNmpgEoJBPWVw",
                "title": "Ein Feuerwerk der Musik | Slavko Avsenik &amp; seine Original Oberkrainer",
                "description": "",
                "thumbnails": {
                    "default": {
                        "url": "https://i.ytimg.com/vi/4GMzb-89XKI/default.jpg",
                        "width": 120,
                        "height": 90
                    },
                    "medium": {
                        "url": "https://i.ytimg.com/vi/4GMzb-89XKI/mqdefault.jpg",
                        "width": 320,
                        "height": 180
                    },
                    "high": {
                        "url": "https://i.ytimg.com/vi/4GMzb-89XKI/hqdefault.jpg",
                        "width": 480,
                        "height": 360
                    }
                },
                "channelTitle": "Musik aus der Heimat",
                "liveBroadcastContent": "none"
            }
        },
        "enriched": true
    }
]